ingest_service_api/__init__.py
ingest_service_api/_impl.py
ingest_service_api/py.typed
ingest_service_api/ingest/__init__.py
ingest_service_api-0.1.0.dist-info/METADATA
ingest_service_api-0.1.0.dist-info/WHEEL
ingest_service_api-0.1.0.dist-info/top_level.txt
ingest_service_api-0.1.0.dist-info/RECORD
